meguru_tokenizer/__init__.py
meguru_tokenizer/__version__.py
meguru_tokenizer/base_tokenizer.py
meguru_tokenizer/sentencepiece_tokenizer.py
meguru_tokenizer/sudachi_tokenizer.py
meguru_tokenizer/vocab.py
meguru_tokenizer/whitespace_tokenizer.py
meguru_tokenizer/process/__init__.py
meguru_tokenizer/process/noise_pytorch.py
meguru_tokenizer/process/noise_tf.py
meguru_tokenizer-0.3.1.dist-info/METADATA
meguru_tokenizer-0.3.1.dist-info/WHEEL
meguru_tokenizer-0.3.1.dist-info/top_level.txt
meguru_tokenizer-0.3.1.dist-info/RECORD
