Metadata-Version: 2.1
Name: meguru-tokenizer
Version: 0.3.1
Summary: simple tokenizer for tensorflow 2.x and PyTorch
Home-page: https://github.com/MokkeMeguru/meguru_tokenizer
Author: MokkeMeguru
Author-email: meguru.mokke@gmail.com
License: MIT license
Keywords: tensorflow,pytorch,tokenizer,nlp
Platform: UNKNOWN
Classifier: Development Status :: 2 - Pre-Alpha
Classifier: Intended Audience :: Developers
Classifier: License :: OSI Approved :: MIT License
Classifier: Natural Language :: English
Classifier: Programming Language :: Python :: 3
Classifier: Programming Language :: Python :: 3.5
Classifier: Programming Language :: Python :: 3.6
Classifier: Programming Language :: Python :: 3.7
Classifier: Programming Language :: Python :: 3.8
Requires-Python: >=3.5
Requires-Dist: ginza (>=4.0.0)
Requires-Dist: sentencepiece
Requires-Dist: neologdn
Requires-Dist: nltk
Requires-Dist: spacy (>=2.2.4)
Requires-Dist: sudachidict-full
Requires-Dist: torch
Requires-Dist: tensorflow (>=2.2.0)
